M2_ProposalTools/FilterImages.py
M2_ProposalTools/MakeRMSmap.py
M2_ProposalTools/ModelFitting.py
M2_ProposalTools/WorkHorse.py
M2_ProposalTools/__init__.py
M2_ProposalTools/analytic_integrations.py
M2_ProposalTools/numerical_integration.py
M2_ProposalTools/py.typed
M2_ProposalTools/xfer_Function_2p5_21Aonly_PCA5_0f08Filtering.txt
M2_ProposalTools/xfer_Function_3p0_21Aonly_PCA5_0f08Filtering.txt
M2_ProposalTools/xfer_Function_3p5_21Aonly_PCA5_0f08Filtering.txt
M2_ProposalTools/xfer_Function_4p0_21Aonly_PCA5_0f08Filtering.txt
M2_ProposalTools/xfer_Function_4p5_21Aonly_PCA5_0f08Filtering.txt
M2_ProposalTools/xfer_Function_5p0_21Aonly_PCA5_0f08Filtering.txt
an_example_package-1.1.0.dist-info/LICENSE
an_example_package-1.1.0.dist-info/METADATA
an_example_package-1.1.0.dist-info/WHEEL
an_example_package-1.1.0.dist-info/top_level.txt
an_example_package-1.1.0.dist-info/RECORD
